libfaketimefs/__init__.py
libfaketimefs/vendored/__init__.py
libfaketimefs/vendored/fusepy/__init__.py
libfaketimefs/vendored/fusepy/fuse.py
libfaketimefs/vendored/fusepy/fusell.py
libfaketimefs/vendored/fusepy/setup.py
libfaketimefs-0.0.4.data/scripts/libfaketimefs
libfaketimefs-0.0.4.dist-info/DESCRIPTION.rst
libfaketimefs-0.0.4.dist-info/METADATA
libfaketimefs-0.0.4.dist-info/RECORD
libfaketimefs-0.0.4.dist-info/WHEEL
libfaketimefs-0.0.4.dist-info/metadata.json
libfaketimefs-0.0.4.dist-info/top_level.txt
