Metadata-Version: 2.0
Name: libfaketimefs
Version: 0.0.4
Summary: Dynamic faketimerc file using a FUSE filesystem
Home-page: https://github.com/claranet/libfaketimefs
Author: Raymond Butcher
Author-email: ray.butcher@claranet.uk
License: MIT License
Platform: UNKNOWN
